suricataparser/__init__.py
suricataparser/exceptions.py
suricataparser/parse.py
suricataparser/rule.py
suricataparser-1.0.0.dist-info/LICENSE
suricataparser-1.0.0.dist-info/WHEEL
suricataparser-1.0.0.dist-info/METADATA
suricataparser-1.0.0.dist-info/RECORD
