Metadata-Version: 2.1
Name: suricataparser
Version: 1.0.0
Summary: Package for parsing and generating Snort/Suricata rules.
License: Apache-2.0
Keywords: suricata,snort,rules
Author: Mikhail Tsyganov
Author-email: tsyganov.michail@yandex.ru
Requires-Python: >=3.7,<4.0
Classifier: Development Status :: 5 - Production/Stable
Classifier: Intended Audience :: Developers
Classifier: License :: OSI Approved :: Apache Software License
Classifier: Operating System :: OS Independent
Classifier: Programming Language :: Python :: 3
Classifier: Programming Language :: Python :: 3 :: Only
Classifier: Programming Language :: Python :: 3.10
Classifier: Programming Language :: Python :: 3.7
Classifier: Programming Language :: Python :: 3.8
Classifier: Programming Language :: Python :: 3.9
